cellprofiler_library/__init__.py
cellprofiler_library/_version.py
cellprofiler_library/py.typed
cellprofiler_library/types.py
cellprofiler_library/functions/__init__.py
cellprofiler_library/functions/file_processing.py
cellprofiler_library/functions/image_processing.py
cellprofiler_library/functions/measurement.py
cellprofiler_library/functions/object_processing.py
cellprofiler_library/functions/segmentation.py
cellprofiler_library/modules/__init__.py
cellprofiler_library/modules/_closing.py
cellprofiler_library/modules/_colortogray.py
cellprofiler_library/modules/_combineobjects.py
cellprofiler_library/modules/_convertimagetoobjects.py
cellprofiler_library/modules/_convertobjectstoimage.py
cellprofiler_library/modules/_correctilluminationapply.py
cellprofiler_library/modules/_crop.py
cellprofiler_library/modules/_dilateimage.py
cellprofiler_library/modules/_enhanceedges.py
cellprofiler_library/modules/_enhanceorsuppressfeatures.py
cellprofiler_library/modules/_erodeimage.py
cellprofiler_library/modules/_erodeobjects.py
cellprofiler_library/modules/_expandorshrinkobjects.py
cellprofiler_library/modules/_fillobjects.py
cellprofiler_library/modules/_gaussianfilter.py
cellprofiler_library/modules/_measureimageoverlap.py
cellprofiler_library/modules/_measureobjectsizeshape.py
cellprofiler_library/modules/_medialaxis.py
cellprofiler_library/modules/_medianfilter.py
cellprofiler_library/modules/_morphologicalskeleton.py
cellprofiler_library/modules/_opening.py
cellprofiler_library/modules/_overlayobjects.py
cellprofiler_library/modules/_reducenoise.py
cellprofiler_library/modules/_savecroppedobjects.py
cellprofiler_library/modules/_threshold.py
cellprofiler_library/modules/_watershed.py
cellprofiler_library/opts/__init__.py
cellprofiler_library/opts/colortogray.py
cellprofiler_library/opts/convertimagetoobjects.py
cellprofiler_library/opts/convertobjectstoimage.py
cellprofiler_library/opts/correctilluminationapply.py
cellprofiler_library/opts/crop.py
cellprofiler_library_nightly-5.0.0.dev340.dist-info/licenses/LICENSE
cellprofiler_library_nightly-5.0.0.dev340.dist-info/METADATA
cellprofiler_library_nightly-5.0.0.dev340.dist-info/WHEEL
cellprofiler_library_nightly-5.0.0.dev340.dist-info/top_level.txt
cellprofiler_library_nightly-5.0.0.dev340.dist-info/RECORD
